[
    {
        "PALL": {
            "clip_prompt": 0.35528528690338135,
            "bbox_clip_prompt": 0.35528528690338135
        },
        "P000": {
            "clip_prompt": 0.38487565517425537,
            "bbox_clip_prompt": 0.361836701631546
        },
        "P001": {
            "clip_prompt": 0.4134446680545807,
            "bbox_clip_prompt": 0.39585763216018677
        },
        "P002": {
            "clip_prompt": 0.3498079776763916,
            "bbox_clip_prompt": 0.3197263181209564
        },
        "P003": {
            "clip_prompt": 0.2934941053390503,
            "bbox_clip_prompt": 0.273860365152359
        },
        "P004": {
            "clip_prompt": 0.35148775577545166,
            "bbox_clip_prompt": 0.3386540114879608
        },
        "P005": {
            "clip_prompt": 0.30680420994758606,
            "bbox_clip_prompt": 0.2829210162162781
        },
        "P006": {
            "clip_prompt": 0.413188099861145,
            "bbox_clip_prompt": 0.3930718004703522
        },
        "P007": {
            "clip_prompt": 0.37031203508377075,
            "bbox_clip_prompt": 0.35335415601730347
        },
        "P008": {
            "clip_prompt": 0.4136459529399872,
            "bbox_clip_prompt": 0.39545559883117676
        }
    },
    {
        "PALL": {
            "clip_prompt": 0.3438258767127991,
            "bbox_clip_prompt": 0.3438258767127991
        },
        "P000": {
            "clip_prompt": 0.35214751958847046,
            "bbox_clip_prompt": 0.34594887495040894
        },
        "P001": {
            "clip_prompt": 0.4046756625175476,
            "bbox_clip_prompt": 0.3929268717765808
        },
        "P002": {
            "clip_prompt": 0.36537033319473267,
            "bbox_clip_prompt": 0.35134196281433105
        },
        "P003": {
            "clip_prompt": 0.2952613830566406,
            "bbox_clip_prompt": 0.2572755515575409
        },
        "P004": {
            "clip_prompt": 0.3612011969089508,
            "bbox_clip_prompt": 0.3414427638053894
        },
        "P005": {
            "clip_prompt": 0.35871636867523193,
            "bbox_clip_prompt": 0.34789228439331055
        },
        "P006": {
            "clip_prompt": 0.4166836440563202,
            "bbox_clip_prompt": 0.35702699422836304
        },
        "P007": {
            "clip_prompt": 0.35606101155281067,
            "bbox_clip_prompt": 0.32793349027633667
        },
        "P008": {
            "clip_prompt": 0.38641422986984253,
            "bbox_clip_prompt": 0.3479260504245758
        }
    },
    {
        "PALL": {
            "clip_prompt": 0.36492830514907837,
            "bbox_clip_prompt": 0.36492830514907837
        },
        "P000": {
            "clip_prompt": 0.37591448426246643,
            "bbox_clip_prompt": 0.35014405846595764
        },
        "P001": {
            "clip_prompt": 0.4050004184246063,
            "bbox_clip_prompt": 0.39110875129699707
        },
        "P002": {
            "clip_prompt": 0.35264089703559875,
            "bbox_clip_prompt": 0.30061841011047363
        },
        "P003": {
            "clip_prompt": 0.3109540641307831,
            "bbox_clip_prompt": 0.2962331771850586
        },
        "P004": {
            "clip_prompt": 0.3673590123653412,
            "bbox_clip_prompt": 0.3533627390861511
        },
        "P005": {
            "clip_prompt": 0.33944952487945557,
            "bbox_clip_prompt": 0.29668915271759033
        },
        "P006": {
            "clip_prompt": 0.4103899598121643,
            "bbox_clip_prompt": 0.3846428096294403
        },
        "P007": {
            "clip_prompt": 0.3477422595024109,
            "bbox_clip_prompt": 0.3214213252067566
        },
        "P008": {
            "clip_prompt": 0.4071400463581085,
            "bbox_clip_prompt": 0.3719257116317749
        }
    },
    {
        "PALL": {
            "clip_prompt": 0.32582804560661316,
            "bbox_clip_prompt": 0.32582804560661316
        },
        "P000": {
            "clip_prompt": 0.37147870659828186,
            "bbox_clip_prompt": 0.35838374495506287
        },
        "P001": {
            "clip_prompt": 0.4086635708808899,
            "bbox_clip_prompt": 0.3835943639278412
        },
        "P002": {
            "clip_prompt": 0.3795032799243927,
            "bbox_clip_prompt": 0.3555893301963806
        },
        "P003": {
            "clip_prompt": 0.3312835395336151,
            "bbox_clip_prompt": 0.3006998300552368
        },
        "P004": {
            "clip_prompt": 0.36362186074256897,
            "bbox_clip_prompt": 0.33886903524398804
        },
        "P005": {
            "clip_prompt": 0.33875200152397156,
            "bbox_clip_prompt": 0.3324663043022156
        },
        "P006": {
            "clip_prompt": 0.39341145753860474,
            "bbox_clip_prompt": 0.36677125096321106
        },
        "P007": {
            "clip_prompt": 0.34907591342926025,
            "bbox_clip_prompt": 0.348272442817688
        },
        "P008": {
            "clip_prompt": 0.39757758378982544,
            "bbox_clip_prompt": 0.3816996216773987
        }
    }
]